djangocms_pai_newsletter/__init__.py
djangocms_pai_newsletter/admin.py
djangocms_pai_newsletter/apps.py
djangocms_pai_newsletter/models.py
djangocms_pai_newsletter/tests.py
djangocms_pai_newsletter/urls.py
djangocms_pai_newsletter/views.py
djangocms_pai_newsletter/migrations/0001_initial.py
djangocms_pai_newsletter/migrations/__init__.py
djangocms_pai_newsletter/templates/djangocms_pai_newsletter/subscribe_form.html
djangocms_pai_newsletter-0.0.2.dist-info/AUTHORS.rst
djangocms_pai_newsletter-0.0.2.dist-info/LICENSE.txt
djangocms_pai_newsletter-0.0.2.dist-info/METADATA
djangocms_pai_newsletter-0.0.2.dist-info/WHEEL
djangocms_pai_newsletter-0.0.2.dist-info/top_level.txt
djangocms_pai_newsletter-0.0.2.dist-info/RECORD
